test/__init__.py
test/test_billing_api.py
test/test_builds_api.py
test/test_buildtargets_api.py
test/test_config_api.py
test/test_credentials_api.py
test/test_inline_response200.py
test/test_inline_response2001.py
test/test_inline_response20010.py
test/test_inline_response20011.py
test/test_inline_response20012.py
test/test_inline_response2002.py
test/test_inline_response2003.py
test/test_inline_response2004.py
test/test_inline_response2005.py
test/test_inline_response2006.py
test/test_inline_response2007.py
test/test_inline_response2008.py
test/test_inline_response2009.py
test/test_options.py
test/test_options1.py
test/test_options10.py
test/test_options2.py
test/test_options3.py
test/test_options4.py
test/test_options5.py
test/test_options6.py
test/test_options7.py
test/test_options8.py
test/test_options9.py
test/test_orgs_api.py
test/test_orgsorgidcredentialssigningandroid_keystore.py
test/test_orgsorgidcredentialssigningios_provisioning_profile.py
test/test_orgsorgidcredentialssigningosx_certificate.py
test/test_orgsorgidprojectsprojectidartifactsdelete_builds.py
test/test_orgsorgidprojectsprojectidauditlog_lines.py
test/test_orgsorgidprojectsprojectidbuildtargets_build_report.py
test/test_orgsorgidprojectsprojectidbuildtargets_builds.py
test/test_orgsorgidprojectsprojectidbuildtargets_credentials.py
test/test_orgsorgidprojectsprojectidbuildtargets_credentials1.py
test/test_orgsorgidprojectsprojectidbuildtargets_credentials1_signing.py
test/test_orgsorgidprojectsprojectidbuildtargets_credentials_signing.py
test/test_orgsorgidprojectsprojectidbuildtargets_credentials_signing_credential_resource_ref.py
test/test_orgsorgidprojectsprojectidbuildtargets_credentials_signing_credential_resource_ref_certificate.py
test/test_orgsorgidprojectsprojectidbuildtargets_credentials_signing_credential_resource_ref_keystore.py
test/test_orgsorgidprojectsprojectidbuildtargets_credentials_signing_credential_resource_ref_provisioning_profile.py
ucb_client-22.7.12.dist-info/LICENSE
ucb_client-22.7.12.dist-info/METADATA
ucb_client-22.7.12.dist-info/NOTICE
ucb_client-22.7.12.dist-info/WHEEL
ucb_client-22.7.12.dist-info/top_level.txt
ucb_client-22.7.12.dist-info/RECORD
