Metadata-Version: 2.1
Name: ucb-client
Version: 22.7.12
Summary: Unity Cloud Build
Home-page: https://github.com/Cookieees/ucb-client
Author-email: artemartsoul@gmail.com
Keywords: Swagger,Unity Cloud Build,UCB
License-File: LICENSE
License-File: NOTICE
Requires-Dist: certifi (>=2017.4.17)
Requires-Dist: python-dateutil (>=2.1)
Requires-Dist: six (>=1.10)
Requires-Dist: urllib3 (>=1.23)
